sync_roles/__init__.py
sync_roles/core.py
sync_roles/models.py
sync_roles/py.typed
sync_roles/adapters/__init__.py
sync_roles/adapters/base.py
sync_roles/adapters/postgres.py
sync_roles-0.0.2.dist-info/licenses/LICENSE
sync_roles-0.0.2.dist-info/METADATA
sync_roles-0.0.2.dist-info/WHEEL
sync_roles-0.0.2.dist-info/top_level.txt
sync_roles-0.0.2.dist-info/RECORD
