Metadata-Version: 2.4
Name: sync-roles
Version: 0.0.2
Summary: Python utility function to ensure that a DB roles have certain permissions.
Author-email: Roberto Lapuente Romo <roberto@lapuente.me>, Department for Business and Trade <sre@digital.trade.gov.uk>
Maintainer-email: Roberto Lapuente Romo <roberto@lapuente.me>
License-Expression: MIT
Project-URL: Repository, https://github.com/elpinchetopo/sync-roles
Classifier: Programming Language :: Python :: 3
Classifier: Operating System :: OS Independent
Requires-Python: ~=3.12.0
License-File: LICENSE
Requires-Dist: sqlalchemy>=1.4.24
Provides-Extra: postgres-psycopg2
Requires-Dist: psycopg2-binary>=2.9.0; extra == "postgres-psycopg2"
Provides-Extra: postgres-psycopg3
Requires-Dist: psycopg>=3.1.0; extra == "postgres-psycopg3"
Provides-Extra: postgres
Requires-Dist: psycopg>=3.1.0; extra == "postgres"
Dynamic: license-file
